src/__init__.py
src/common/__init__.py
src/common/config.py
src/common/utils/__init__.py
src/common/utils/from_xlsx_to_json.py
src/common/valuesets_data.py
src/grpcapi/__init__.py
src/grpcapi/ensembl/__init__.py
src/grpcapi/ensembl/client.py
src/grpcapi/ensembl/server.py
src/grpcapi/ensembl/valuesets/__init__.py
src/grpcapi/ensembl/valuesets/valuesets_pb2.py
src/grpcapi/ensembl/valuesets/valuesets_pb2_grpc.py
src/rest/__init__.py
src/rest/handler.py
src/rest/model/__init__.py
src/rest/model/error_response.py
src/rest/model/value_set_item.py
src/rest/routes.py
src/rest/server.py
src/test/__init__.py
src/test/data/valuesets.json
src/test/test_rest_routes.py
src/test/test_valueset_data.py
src/test/test_valueset_servicer.py
ensembl_valuesets-0.1.0.dist-info/LICENSE
ensembl_valuesets-0.1.0.dist-info/METADATA
ensembl_valuesets-0.1.0.dist-info/WHEEL
ensembl_valuesets-0.1.0.dist-info/entry_points.txt
ensembl_valuesets-0.1.0.dist-info/RECORD
