Metadata-Version: 2.1
Name: ensembl-valuesets
Version: 0.1.0
Summary: Ensembl ValueSets gRPC/REST API
Home-page: https://www.ensembl.org
License: Apache-2.0
Author: Ensembl
Author-email: dev@ensembl.org
Requires-Python: >=3.10,<4.0
Classifier: License :: OSI Approved :: Apache Software License
Classifier: Programming Language :: Python :: 3
Classifier: Programming Language :: Python :: 3.10
Classifier: Programming Language :: Python :: 3.11
Requires-Dist: fastapi (>=0.95.0,<0.96.0)
Requires-Dist: grpcio (>=1.54.0,<2.0.0)
Requires-Dist: grpcio-tools (>=1.54.0,<2.0.0)
Requires-Dist: openpyxl (>=3.1.2,<4.0.0)
Requires-Dist: pandas (>=2.0.1,<3.0.0)
Requires-Dist: protobuf (>=4.22.3,<5.0.0)
Requires-Dist: pydantic (>=1.10,<2.0)
Requires-Dist: requests (>=2.28.2,<3.0.0)
Requires-Dist: typer (>=0.9,<0.10)
Requires-Dist: uvicorn (>=0.22.0,<0.23.0)
Project-URL: Repository, https://github.com/Ensembl/ensembl-valuesets-api
